x64rdbgpy/__init__.py
x64rdbgpy/breakpoint.py
x64rdbgpy/bridgemain.py
x64rdbgpy/debug.py
x64rdbgpy/memory.py
x64rdbgpy/module.py
x64rdbgpy/register.py
x64rdbgpy/x64rdbg.py
x64rdbgpy/proto/__init__.py
x64rdbgpy/proto/base_pb2.py
x64rdbgpy/proto/base_pb2_grpc.py
x64rdbgpy/proto/bridgemain_pb2.py
x64rdbgpy/proto/bridgemain_pb2_grpc.py
x64rdbgpy/proto/debug_pb2.py
x64rdbgpy/proto/debug_pb2_grpc.py
x64rdbgpy/proto/memory_pb2.py
x64rdbgpy/proto/memory_pb2_grpc.py
x64rdbgpy/proto/module_pb2.py
x64rdbgpy/proto/module_pb2_grpc.py
x64rdbgpy/proto/register_pb2.py
x64rdbgpy/proto/register_pb2_grpc.py
x64rdbgpy/wrapper/__init__.py
x64rdbgpy/wrapper/breakpoint.py
x64rdbgpy/wrapper/bridgemain.py
x64rdbgpy/wrapper/debug.py
x64rdbgpy/wrapper/memory.py
x64rdbgpy/wrapper/module.py
x64rdbgpy/wrapper/register.py
x64rdbgpy-0.0.2.dist-info/METADATA
x64rdbgpy-0.0.2.dist-info/WHEEL
x64rdbgpy-0.0.2.dist-info/top_level.txt
x64rdbgpy-0.0.2.dist-info/RECORD
